dynforms/__init__.py
dynforms/admin.py
dynforms/apps.py
dynforms/dynfields.py
dynforms/fields.py
dynforms/forms.py
dynforms/migrations/0001_initial.py
dynforms/migrations/0002_formtype_header.py
dynforms/migrations/0003_formtype_help_bar_alter_formtype_header.py
dynforms/migrations/0004_formtype_wizard.py
dynforms/migrations/0005_fix_score_choices.py
dynforms/migrations/0006_fix_likert_choices.py
dynforms/migrations/0007_update_likert_scores.py
dynforms/migrations/__init__.py
dynforms/models.py
dynforms/static/dynforms/builder.min.css
dynforms/static/dynforms/builder.min.css.map
dynforms/static/dynforms/builder.scss
dynforms/static/dynforms/countries.js
dynforms/static/dynforms/countries.min.js
dynforms/static/dynforms/df-toasts.js
dynforms/static/dynforms/df-toasts.min.js
dynforms/static/dynforms/dynforms.js
dynforms/static/dynforms/dynforms.min.css
dynforms/static/dynforms/dynforms.min.css.map
dynforms/static/dynforms/dynforms.min.js
dynforms/static/dynforms/dynforms.scss
dynforms/static/dynforms/icons.yml
dynforms/static/dynforms/jquery-bs-datepicker.js
dynforms/static/dynforms/jquery-bs-datepicker.min.css
dynforms/static/dynforms/jquery-bs-datepicker.min.css.map
dynforms/static/dynforms/jquery-bs-datepicker.min.js
dynforms/static/dynforms/jquery-bs-datepicker.scss
dynforms/static/dynforms/jquery-clock-timepicker.js
dynforms/static/dynforms/jquery-clock-timepicker.min.js
dynforms/static/dynforms/trumbowyg.mathjax.js
dynforms/static/dynforms/trumbowyg.mathjax.min.js
dynforms/templates/dynforms/base.html
dynforms/templates/dynforms/builder.html
dynforms/templates/dynforms/edit-settings.html
dynforms/templates/dynforms/field-choices.html
dynforms/templates/dynforms/field-menu.html
dynforms/templates/dynforms/field-named-choices.html
dynforms/templates/dynforms/field-scores.html
dynforms/templates/dynforms/field-values.html
dynforms/templates/dynforms/field.html
dynforms/templates/dynforms/fields/address.html
dynforms/templates/dynforms/fields/checkboxes.html
django_dynforms-2025.9.11.dist-info/METADATA
django_dynforms-2025.9.11.dist-info/WHEEL
django_dynforms-2025.9.11.dist-info/licenses/LICENSE
django_dynforms-2025.9.11.dist-info/RECORD
