Metadata-Version: 2.4
Name: django-dynforms
Version: 2025.9.11
Summary: A Django reusable App for dynamically designing and generating forms.
License-Expression: MIT
License-File: LICENSE
Author: Michel Fodje
Author-email: michel4j@gmail.com
Requires-Python: >=3.10
Classifier: Environment :: Web Environment
Classifier: Framework :: Django
Classifier: Framework :: Django :: 4.2
Classifier: Framework :: Django :: 5.0
Classifier: Framework :: Django :: 5.1
Classifier: Framework :: Django :: 5.2
Classifier: Intended Audience :: Developers
Classifier: License :: OSI Approved :: MIT License
Classifier: Operating System :: OS Independent
Classifier: Programming Language :: Python
Classifier: Programming Language :: Python :: 3
Classifier: Programming Language :: Python :: 3.10
Classifier: Programming Language :: Python :: 3.11
Classifier: Programming Language :: Python :: 3.12
Classifier: Programming Language :: Python :: 3.13
Classifier: Topic :: Internet :: WWW/HTTP
Classifier: Topic :: Internet :: WWW/HTTP :: Dynamic Content
Classifier: Topic :: Software Development :: Libraries :: Application Frameworks
Classifier: Topic :: Software Development :: Libraries :: Python Modules
Requires-Dist: django (>=5.2.7,<6.0.0)
Requires-Dist: django-crisp-modals (>=2025.10.0)
Requires-Dist: django-itemlist (>=2025.7.7)
Requires-Dist: markdown (>=3.8,<4.0)
Requires-Dist: numpy (>=2.2.4,<3.0.0)
Requires-Dist: py-dateutil (>=2.2,<3.0)
Requires-Dist: pycryptodome (>=3.23.0,<4.0.0)
Requires-Dist: pygments (>=2.19.1,<3.0.0)
Requires-Dist: pyparsing (>=3.2.1,<4.0.0)
Requires-Dist: pyyaml (>=6.0.3)
Requires-Dist: requests (>=2.32.5)
Project-URL: Homepage, https://github.com/michel4j/django-dynforms
Project-URL: Issues, https://github.com/michel4j/django-dynforms/issues
